spmlab/__init__.py
spmlab/formats/__init__.py
spmlab/formats/sm4/__init__.py
spmlab/formats/sm4/abstract.py
spmlab/formats/sm4/image.py
spmlab/formats/sm4/iz.py
spmlab/formats/sm4/read.py
spmlab/formats/sm4/sts.py
spmlab/readers/spym/__init__.py
spmlab/readers/spym/_accessors/__init__.py
spmlab/readers/spym/_version.py
spmlab/readers/spym/io/__init__.py
spmlab/readers/spym/io/load.py
spmlab/readers/spym/io/rhksm4/.gitkeep
spmlab/readers/spym/io/rhksm4/__init__.py
spmlab/readers/spym/io/rhksm4/_methods.py
spmlab/readers/spym/io/rhksm4/_sm4.py
spmlab/readers/spym/process/__init__.py
spmlab/readers/spym/process/filters.py
spmlab/readers/spym/process/level.py
spmlab-1.1.22.dist-info/LICENSE.txt
spmlab-1.1.22.dist-info/METADATA
spmlab-1.1.22.dist-info/WHEEL
spmlab-1.1.22.dist-info/RECORD
